<PAMDataset>
  <Metadata domain="IMAGE_STRUCTURE">
    <MDI key="COMPRESSION">JPEG</MDI>
    <MDI key="INTERLEAVE">PIXEL</MDI>
    <MDI key="SOURCE_COLOR_SPACE">YCbCr</MDI>
  </Metadata>
  <PAMRasterBand band="1">
    <Metadata domain="IMAGE_STRUCTURE">
      <MDI key="COMPRESSION">JPEG</MDI>
    </Metadata>
    <Metadata>
      <MDI key="STATISTICS_MAXIMUM">107</MDI>
      <MDI key="STATISTICS_MEAN">44.393901239897</MDI>
      <MDI key="STATISTICS_MINIMUM">22</MDI>
      <MDI key="STATISTICS_STDDEV">13.731258001987</MDI>
      <MDI key="STATISTICS_VALID_PERCENT">100</MDI>
    </Metadata>
  </PAMRasterBand>
  <PAMRasterBand band="2">
    <Metadata domain="IMAGE_STRUCTURE">
      <MDI key="COMPRESSION">JPEG</MDI>
    </Metadata>
    <Metadata>
      <MDI key="STATISTICS_MAXIMUM">210</MDI>
      <MDI key="STATISTICS_MEAN">160.46631652157</MDI>
      <MDI key="STATISTICS_MINIMUM">67</MDI>
      <MDI key="STATISTICS_STDDEV">26.997973373294</MDI>
      <MDI key="STATISTICS_VALID_PERCENT">100</MDI>
    </Metadata>
  </PAMRasterBand>
  <PAMRasterBand band="3">
    <Metadata domain="IMAGE_STRUCTURE">
      <MDI key="COMPRESSION">JPEG</MDI>
    </Metadata>
    <Metadata>
      <MDI key="STATISTICS_MAXIMUM">164</MDI>
      <MDI key="STATISTICS_MEAN">129.30162841451</MDI>
      <MDI key="STATISTICS_MINIMUM">95</MDI>
      <MDI key="STATISTICS_STDDEV">11.231132683475</MDI>
      <MDI key="STATISTICS_VALID_PERCENT">100</MDI>
    </Metadata>
  </PAMRasterBand>
</PAMDataset>
